CHANGES.txt
LICENSE.txt
README.txt
setup.py
src/getpaid/__init__.py
src/getpaid.pxpay.egg-info/PKG-INFO
src/getpaid.pxpay.egg-info/SOURCES.txt
src/getpaid.pxpay.egg-info/dependency_links.txt
src/getpaid.pxpay.egg-info/namespace_packages.txt
src/getpaid.pxpay.egg-info/not-zip-safe
src/getpaid.pxpay.egg-info/requires.txt
src/getpaid.pxpay.egg-info/top_level.txt
src/getpaid/pxpay/README.txt
src/getpaid/pxpay/TODO.txt
src/getpaid/pxpay/__init__.py
src/getpaid/pxpay/certs.pem
src/getpaid/pxpay/config.py
src/getpaid/pxpay/configure.zcml
src/getpaid/pxpay/errors.py
src/getpaid/pxpay/exceptions.py
src/getpaid/pxpay/gateway.py
src/getpaid/pxpay/interfaces.py
src/getpaid/pxpay/overrides.zcml
src/getpaid/pxpay/parser.py
src/getpaid/pxpay/pxpay.py
src/getpaid/pxpay/utils.py
src/getpaid/pxpay/vocabulary.py
src/getpaid/pxpay/vocabulary.zcml
src/getpaid/pxpay/workflow.py
src/getpaid/pxpay/browser/__init__.py
src/getpaid/pxpay/browser/callback.py
src/getpaid/pxpay/browser/checkout.py
src/getpaid/pxpay/browser/configure.zcml
src/getpaid/pxpay/browser/errors.py
src/getpaid/pxpay/browser/templates/checkout-review-pay.pt
src/getpaid/pxpay/browser/templates/pxpay-communication-error.pt
src/getpaid/pxpay/tests/__init__.py
src/getpaid/pxpay/tests/base.py
src/getpaid/pxpay/tests/callback.txt
src/getpaid/pxpay/tests/helpers.py
src/getpaid/pxpay/tests/parser.txt
src/getpaid/pxpay/tests/paymentprocessor.txt
src/getpaid/pxpay/tests/test_doctests.py
src/getpaid/pxpay/tests/utils.py
src/getpaid/pxpay/tests/utils.txt