Metadata-Version: 1.0
Name: getpaid.pxpay
Version: 0.5
Summary: PXPay payment plugin
Home-page: UNKNOWN
Author: getpaid community
Author-email: getpaid-dev@googlegroups.com
License: ZPL
Keywords: getpaid pxpay payment
Platform: UNKNOWN
Classifier: Framework :: Plone
Classifier: Programming Language :: Python
Classifier: Framework :: Zope3
Classifier: Intended Audience :: Developers
Classifier: License :: OSI Approved :: Zope Public License
Classifier: Operating System :: OS Independent
Classifier: Topic :: Office/Business :: Financial
Classifier: Topic :: Software Development :: Libraries
